{
    "header_items": [
        {
            "name": "order_id",
            "width": "14"
        },
        {
            "name": "shop_name",
            "width": "20"
        },
        {
            "name": "product_id",
            "width": "20"
        },
        {
            "name": "product_name",
            "width": "39"
        },
        {
            "name": "goods_number",
            "width": "6"
        },
        {
            "name": "amount",
            "width": "13"
        },
        {
            "name": "jingdou",
            "width": "6"
        },
        {
            "name": "order_time",
            "width": "25"
        },
        {
            "name": "order_status",
            "width": "8"
        },
        {
            "name": "courier_services_company",
            "width": "10"
        },
        {
            "name": "courier_number",
            "width": "20"
        },
        {
            "name": "consignee_name",
            "width": "8"
        },
        {
            "name": "consignee_address",
            "width": "50"
        },
        {
            "name": "consignee_phone_number",
            "width": "22"
        },
        {
            "name": "order_url",
            "width": "30"
        }
    ]
}